lw2/__init__.py
lw2/commands.py
lw2/handler.py
lw2/lightware.py
lw2-0.1.0.dist-info/METADATA
lw2-0.1.0.dist-info/WHEEL
lw2-0.1.0.dist-info/licenses/LICENSE
lw2-0.1.0.dist-info/RECORD
