Metadata-Version: 2.4
Name: lw2
Version: 0.1.0
Summary: Lightware LW2 API
Author-email: Intermediate Engineering GmbH <info@im-en.com>
License-Expression: MIT
License-File: LICENSE
Classifier: Programming Language :: Python :: 3 :: Only
Classifier: Programming Language :: Python :: 3.10
Classifier: Programming Language :: Python :: 3.11
Classifier: Programming Language :: Python :: 3.12
Classifier: Programming Language :: Python :: 3.13
Requires-Python: >=3.10
